dash_react_bubble_chart/BubbleChart.py
dash_react_bubble_chart/__init__.py
dash_react_bubble_chart/_imports_.py
dash_react_bubble_chart/dash_react_bubble_chart.min.js
dash_react_bubble_chart/dash_react_bubble_chart.min.js.map
dash_react_bubble_chart/metadata.json
dash_react_bubble_chart/package-info.json
dash_react_bubble_chart-0.0.1.dist-info/LICENSE
dash_react_bubble_chart-0.0.1.dist-info/METADATA
dash_react_bubble_chart-0.0.1.dist-info/WHEEL
dash_react_bubble_chart-0.0.1.dist-info/top_level.txt
dash_react_bubble_chart-0.0.1.dist-info/RECORD
