Metadata-Version: 2.1
Name: dash-react-bubble-chart
Version: 0.0.1
Summary: Project Description
Home-page: UNKNOWN
Author: Adam Boyher <aboyher@gmail.com>
Author-email: UNKNOWN
License: MIT
Platform: UNKNOWN
Classifier: Framework :: Dash
